{
  "checks": [
    {
      "label": "calmel",
      "latency_ms": 35,
      "message": "HTTP 200",
      "status": "ok",
      "variant": null
    },
    {
      "label": "DNS",
      "latency_ms": 2,
      "message": "reachable",
      "status": "ok",
      "variant": null
    },
    {
      "label": "HA",
      "latency_ms": 1,
      "message": "HTTP 200",
      "status": "ok",
      "variant": null
    },
    {
      "label": "linuxeye",
      "latency_ms": 2,
      "message": "reachable",
      "status": "ok",
      "variant": null
    },
    {
      "label": "mac",
      "latency_ms": 118,
      "message": "reachable",
      "status": "ok",
      "variant": null
    },
    {
      "label": "rpi remota",
      "message": "sin datos",
      "status": "unknown",
      "variant": "remote"
    }
  ],
  "summary": {
    "failed_checks": 0,
    "label": "Homelab",
    "last_updated": "12/03 10:05:01",
    "last_updated_iso": "2026-03-12T10:05:01.405927+01:00",
    "overall_status": "ok",
    "source": "calmel",
    "total_checks": 6
  }
}